README
setup.py
pylint_web2py/__init__.py
pylint_web2py.egg-info/PKG-INFO
pylint_web2py.egg-info/SOURCES.txt
pylint_web2py.egg-info/dependency_links.txt
pylint_web2py.egg-info/requires.txt
pylint_web2py.egg-info/top_level.txt