Metadata-Version: 1.0
Name: pylint-web2py
Version: 0.1
Summary: pylint-web2py is a Pylint plugin to help reduce false positives due to web2py implicit imports
Home-page: https://github.com/dsludwig/pylint-web2py
Author: Derek Ludwig
Author-email: derek.s.ludwig@gmail.com
License: GPLv2
Keywords: pylint web2py plugin
Platform: UNKNOWN
